TypescriptDeepDive/README.md
TypescriptDeepDive/__init__.py
TypescriptDeepDive/__main__.py
TypescriptDeepDive/file.epub
TypescriptDeepDive/index.html
TypescriptDeepDive/css/__init__.py
TypescriptDeepDive/css/annotations.css
TypescriptDeepDive/css/main.css
TypescriptDeepDive/css/normalize.css
TypescriptDeepDive/css/popup.css
TypescriptDeepDive/font/__init__.py
TypescriptDeepDive/font/fontello.eot
TypescriptDeepDive/font/fontello.svg
TypescriptDeepDive/font/fontello.ttf
TypescriptDeepDive/font/fontello.woff
TypescriptDeepDive/img/__init__.py
TypescriptDeepDive/img/annotator-glyph-sprite.png
TypescriptDeepDive/img/annotator-icon-sprite.png
TypescriptDeepDive/img/apple-touch-icon.png
TypescriptDeepDive/img/cancelfullscreen.png
TypescriptDeepDive/img/close.png
TypescriptDeepDive/img/fullscreen.png
TypescriptDeepDive/img/loader.gif
TypescriptDeepDive/img/menu-icon.png
TypescriptDeepDive/img/save.png
TypescriptDeepDive/img/saved.png
TypescriptDeepDive/img/settings-s.png
TypescriptDeepDive/img/settings.png
TypescriptDeepDive/img/star.png
TypescriptDeepDive/js/__init__.py
TypescriptDeepDive/js/epub.js
TypescriptDeepDive/js/epub.min.js
TypescriptDeepDive/js/epub.min.map
TypescriptDeepDive/js/hooks.min.js
TypescriptDeepDive/js/hooks.min.map
TypescriptDeepDive/js/reader.js
TypescriptDeepDive/js/reader.js.map
TypescriptDeepDive/js/reader.min.js
TypescriptDeepDive/js/reader.min.map
TypescriptDeepDive/js/hooks/__init__.py
TypescriptDeepDive/js/hooks/extensions/__init__.py
TypescriptDeepDive/js/hooks/extensions/highlight.js
TypescriptDeepDive/js/libs/__init__.py
TypescriptDeepDive/js/libs/jquery.min.js
TypescriptDeepDive/js/libs/localforage.min.js
TypescriptDeepDive/js/libs/screenfull.js
TypescriptDeepDive/js/libs/screenfull.min.js
TypescriptDeepDive/js/libs/zip.min.js
TypescriptDeepDive/js/plugins/__init__.py
TypescriptDeepDive/js/plugins/hypothesis.js
TypescriptDeepDive/js/plugins/search.js
typescript_deep_dive-2024.3.2.0.dist-info/METADATA
typescript_deep_dive-2024.3.2.0.dist-info/WHEEL
typescript_deep_dive-2024.3.2.0.dist-info/entry_points.txt
typescript_deep_dive-2024.3.2.0.dist-info/top_level.txt
typescript_deep_dive-2024.3.2.0.dist-info/RECORD
